register_file.v
module register_file(
    input clk,
    input reset,
    input [4:0] rs1,          // Source register 1
    input [4:0] rs2,          // Source register 2
    input [4:0] rd,           // Destination register
    input [31:0] write_data,  // Data to write
    input reg_write,          // Register write enable
    output [31:0] read_data1, // Data from source register 1
    output [31:0] read_data2  // Data from source register 2
);

    // 32 registers, each 32 bits wide
    reg [31:0] registers [0:31];
    integer i;

    // Initialize registers to 0 on reset
    always @(posedge clk or posedge reset) begin
        if (reset) begin
            for (i = 0; i < 32; i = i + 1) begin
                registers[i] <= 32'b0;
            end
        end
        else if (reg_write && rd != 5'b0) begin
            // Register x0 is hardwired to 0 in RISC-V
            registers[rd] <= write_data;
        end
    end

    // Read data from registers
    // Register x0 is hardwired to 0
    assign read_data1 = (rs1 == 5'b0) ? 32'b0 : registers[rs1];
    assign read_data2 = (rs2 == 5'b0) ? 32'b0 : registers[rs2];

endmodule

register_file_tb.v
module register_file_tb;
    // Inputs
    reg clk;
    reg reset;
    reg [4:0] rs1;
    reg [4:0] rs2;
    reg [4:0] rd;
    reg [31:0] write_data;
    reg reg_write;

    // Outputs
    wire [31:0] read_data1;
    wire [31:0] read_data2;

    // Instantiate the Register File
    register_file uut (
        .clk(clk),
        .reset(reset),
        .rs1(rs1),
        .rs2(rs2),
        .rd(rd),
        .write_data(write_data),
        .reg_write(reg_write),
        .read_data1(read_data1),
        .read_data2(read_data2)
    );

    // Clock generation
    always #5 clk = ~clk;

    // Test vectors
    initial begin
        // Initialize inputs
        clk = 0;
        reset = 1;
        rs1 = 0;
        rs2 = 0;
        rd = 0;
        write_data = 0;
        reg_write = 0;

        // Generate VCD file for waveform viewing
        $dumpfile("register_file_tb.vcd");
        $dumpvars(0, register_file_tb);

        // Apply reset
        #10;
        reset = 0;

        // Test writing to register 1
        #10;
        rd = 5'd1;
        write_data = 32'd100;
        reg_write = 1;
        #10;
        reg_write = 0;

        // Test reading from register 1
        rs1 = 5'd1;
        #10;
        if (read_data1 !== 32'd100) $display("Register read test failed: reg[%d] = %d", rs1, read_data1);
        else $display("Register read test passed: reg[%d] = %d", rs1, read_data1);

        // Test writing to register 2
        #10;
        rd = 5'd2;
        write_data = 32'd200;
        reg_write = 1;
        #10;
        reg_write = 0;

        // Test reading from register 2
        rs2 = 5'd2;
        #10;
        if (read_data2 !== 32'd200) $display("Register read test failed: reg[%d] = %d", rs2, read_data2);
        else $display("Register read test passed: reg[%d] = %d", rs2, read_data2);

        // Test writing to register 0 (should remain 0)
        #10;
        rd = 5'd0;
        write_data = 32'd300;
        reg_write = 1;
        #10;
        reg_write = 0;

        // Test reading from register 0
        rs1 = 5'd0;
        #10;
        if (read_data1 !== 32'd0) $display("Register x0 test failed: reg[0] = %d", read_data1);
        else $display("Register x0 test passed: reg[0] = %d", read_data1);

        $display("Register file tests completed");
        $display("To view waveforms, run: gtkwave register_file_tb.vcd");
        $finish;
    end
endmodule

register_file_tb.vcd
$date
	Mon Apr 28 23:52:37 2025
$end
$version
	Icarus Verilog
$end
$timescale
	1s
$end
$scope module register_file_tb $end
$var wire 32 ! read_data2 [31:0] $end
$var wire 32 " read_data1 [31:0] $end
$var reg 1 # clk $end
$var reg 5 $ rd [4:0] $end
$var reg 1 % reg_write $end
$var reg 1 & reset $end
$var reg 5 ' rs1 [4:0] $end
$var reg 5 ( rs2 [4:0] $end
$var reg 32 ) write_data [31:0] $end
$scope module uut $end
$var wire 1 # clk $end
$var wire 5 * rd [4:0] $end
$var wire 1 % reg_write $end
$var wire 1 & reset $end
$var wire 5 + rs1 [4:0] $end
$var wire 5 , rs2 [4:0] $end
$var wire 32 - write_data [31:0] $end
$var wire 32 . read_data2 [31:0] $end
$var wire 32 / read_data1 [31:0] $end
$var integer 32 0 i [31:0] $end
$upscope $end
$upscope $end
$enddefinitions $end
$comment Show the parameter values. $end
$dumpall
$end
#0
$dumpvars
b100000 0
b0 /
b0 .
b0 -
b0 ,
b0 +
b0 *
b0 )
b0 (
b0 '
1&
0%
b0 $
0#
b0 "
b0 !
$end
#5
b100000 0
1#
#10
0#
0&
#15
1#
#20
0#
1%
b1100100 )
b1100100 -
b1 $
b1 *
#25
1#
#30
b1100100 "
b1100100 /
0#
b1 '
b1 +
0%
#35
1#
#40
0#
#45
1#
#50
0#
1%
b11001000 )
b11001000 -
b10 $
b10 *
#55
1#
#60
b11001000 !
b11001000 .
0#
b10 (
b10 ,
0%
#65
1#
#70
0#
#75
1#
#80
0#
1%
b100101100 )
b100101100 -
b0 $
b0 *
#85
1#
#90
b0 "
b0 /
0#
b0 '
b0 +
0%
